distributed_networking_utilities/__init__.py
distributed_networking_utilities/multiproc_arr_recv.py
distributed_networking_utilities/zmq_exchange.py
distributed_networking_utilities-0.0.4.dist-info/METADATA
distributed_networking_utilities-0.0.4.dist-info/WHEEL
distributed_networking_utilities-0.0.4.dist-info/top_level.txt
distributed_networking_utilities-0.0.4.dist-info/RECORD
