Metadata-Version: 2.1
Name: distributed-networking-utilities
Version: 0.0.4
Summary: Utilities for distributed systems construction.
Home-page: https://github.com/roj4s/distributed_networking_utilities
Author: Luis Rojas Aguilera
Author-email: rojas@icomp.ufam.edu.br
License: UNKNOWN
Platform: UNKNOWN
Classifier: Programming Language :: Python :: 3
Classifier: License :: OSI Approved :: MIT License
Classifier: Operating System :: OS Independent
Requires-Dist: numpy (==1.16.4)
Requires-Dist: pkg-resources (==0.0.0)
Requires-Dist: pyzmq (==18.0.1)
Requires-Dist: zmq (==0.0.0)
